{
  "info": {
    "id": 3030,
    "code": "12096",
    "name": "BLACK PVC 2,60X1,70 EST, FLORES BEGE",
    "timestamp": "2026-05-05T20:05:12.454Z"
  },
  "data": {
    "Fábrica": [
      {
        "quantidade": 3,
        "data_evento": "2023-03-20T03:00:00.000Z",
        "natureza": "Transferência Saída Fábrica",
        "operacao": "DEBITO"
      },
      {
        "quantidade": 2,
        "data_evento": "2023-03-20T03:00:00.000Z",
        "natureza": "Transferência Saída Fábrica",
        "operacao": "DEBITO"
      },
      {
        "quantidade": 25,
        "data_evento": "2023-03-20T03:00:00.000Z",
        "natureza": "Entrada Produção",
        "operacao": "CREDITO"
      },
      {
        "quantidade": 3,
        "data_evento": "2023-03-23T03:00:00.000Z",
        "natureza": "Transferência Saída Fábrica",
        "operacao": "DEBITO"
      },
      {
        "quantidade": 2,
        "data_evento": "2023-03-23T03:00:00.000Z",
        "natureza": "Transferência Saída Fábrica",
        "operacao": "DEBITO"
      },
      {
        "quantidade": 1,
        "data_evento": "2023-03-23T03:00:00.000Z",
        "natureza": "Transferência Saída Fábrica",
        "operacao": "DEBITO"
      },
      {
        "quantidade": 2,
        "data_evento": "2023-03-28T03:00:00.000Z",
        "natureza": "Transferência Saída Fábrica",
        "operacao": "DEBITO"
      }
    ],
    "Betim": [
      {
        "quantidade": 2,
        "data_evento": "2023-03-21T03:00:00.000Z",
        "natureza": "Transferência Entrada",
        "operacao": "CREDITO"
      },
      {
        "quantidade": 1,
        "data_evento": "2023-03-29T03:00:00.000Z",
        "natureza": "Venda",
        "operacao": "DEBITO"
      },
      {
        "quantidade": 1,
        "data_evento": "2023-04-04T03:00:00.000Z",
        "natureza": "Venda",
        "operacao": "DEBITO"
      }
    ],
    "Babita": [
      {
        "quantidade": 2,
        "data_evento": "2023-03-21T03:00:00.000Z",
        "natureza": "Transferência Entrada",
        "operacao": "CREDITO"
      },
      {
        "quantidade": 1,
        "data_evento": "2023-03-22T03:00:00.000Z",
        "natureza": "Venda",
        "operacao": "DEBITO"
      },
      {
        "quantidade": 1,
        "data_evento": "2023-03-23T03:00:00.000Z",
        "natureza": "Transferência Entrada",
        "operacao": "CREDITO"
      },
      {
        "quantidade": 1,
        "data_evento": "2023-04-18T03:00:00.000Z",
        "natureza": "Venda",
        "operacao": "DEBITO"
      },
      {
        "quantidade": 1,
        "data_evento": "2023-06-10T03:00:00.000Z",
        "natureza": "Venda",
        "operacao": "DEBITO"
      },
      {
        "quantidade": 1,
        "data_evento": "2023-06-17T03:00:00.000Z",
        "natureza": "Devolução de Venda",
        "operacao": "CREDITO"
      },
      {
        "quantidade": 1,
        "data_evento": "2023-06-26T03:00:00.000Z",
        "natureza": "Venda",
        "operacao": "DEBITO"
      }
    ],
    "Barreiro": [
      {
        "quantidade": 3,
        "data_evento": "2023-03-21T03:00:00.000Z",
        "natureza": "Transferência Entrada",
        "operacao": "CREDITO"
      },
      {
        "quantidade": 1,
        "data_evento": "2023-03-24T03:00:00.000Z",
        "natureza": "Venda",
        "operacao": "DEBITO"
      },
      {
        "quantidade": 2,
        "data_evento": "2023-03-29T03:00:00.000Z",
        "natureza": "Transferência Entrada",
        "operacao": "CREDITO"
      },
      {
        "quantidade": 4,
        "data_evento": "2023-04-10T03:00:00.000Z",
        "natureza": "Venda",
        "operacao": "DEBITO"
      }
    ],
    "Venda Nova": [
      {
        "quantidade": 2,
        "data_evento": "2023-03-21T03:00:00.000Z",
        "natureza": "Transferência Entrada",
        "operacao": "CREDITO"
      },
      {
        "quantidade": 1,
        "data_evento": "2023-03-25T03:00:00.000Z",
        "natureza": "Venda",
        "operacao": "DEBITO"
      },
      {
        "quantidade": 2,
        "data_evento": "2023-03-30T03:00:00.000Z",
        "natureza": "Venda",
        "operacao": "DEBITO"
      },
      {
        "quantidade": 1,
        "data_evento": "2023-03-30T03:00:00.000Z",
        "natureza": "Transferência Entrada",
        "operacao": "CREDITO"
      }
    ],
    "G2": [
      {
        "quantidade": 2,
        "data_evento": "2023-03-21T03:00:00.000Z",
        "natureza": "Transferência Entrada",
        "operacao": "CREDITO"
      },
      {
        "quantidade": 1,
        "data_evento": "2023-03-28T03:00:00.000Z",
        "natureza": "Venda",
        "operacao": "DEBITO"
      },
      {
        "quantidade": 1,
        "data_evento": "2023-03-29T03:00:00.000Z",
        "natureza": "Devolução de Venda",
        "operacao": "CREDITO"
      },
      {
        "quantidade": 1,
        "data_evento": "2023-03-30T03:00:00.000Z",
        "natureza": "Transferência Saída Loja",
        "operacao": "DEBITO"
      }
    ],
    "Guaranis": [
      {
        "quantidade": 2,
        "data_evento": "2023-03-21T03:00:00.000Z",
        "natureza": "Transferência Entrada",
        "operacao": "CREDITO"
      },
      {
        "quantidade": 1,
        "data_evento": "2023-03-22T03:00:00.000Z",
        "natureza": "Venda",
        "operacao": "DEBITO"
      },
      {
        "quantidade": 2,
        "data_evento": "2023-03-25T03:00:00.000Z",
        "natureza": "Transferência Entrada",
        "operacao": "CREDITO"
      },
      {
        "quantidade": 1,
        "data_evento": "2023-04-08T03:00:00.000Z",
        "natureza": "Venda",
        "operacao": "DEBITO"
      },
      {
        "quantidade": 1,
        "data_evento": "2023-04-10T03:00:00.000Z",
        "natureza": "Transferência Entrada",
        "operacao": "CREDITO"
      },
      {
        "quantidade": 2,
        "data_evento": "2023-04-10T03:00:00.000Z",
        "natureza": "Venda",
        "operacao": "DEBITO"
      },
      {
        "quantidade": 1,
        "data_evento": "2023-05-29T03:00:00.000Z",
        "natureza": "Venda",
        "operacao": "DEBITO"
      }
    ]
  }
}