{
  "info": {
    "id": 3978,
    "code": "13108",
    "name": "KIT TB. ESPANHA 19MM (P/ TETO) CROMADO MT",
    "timestamp": "2026-05-05T20:07:47.865Z"
  },
  "data": {
    "Guaranis": [
      {
        "quantidade": 1,
        "data_evento": "2025-10-20T03:00:00.000Z",
        "natureza": "Venda",
        "operacao": "DEBITO"
      },
      {
        "quantidade": 1,
        "data_evento": "2026-03-26T03:00:00.000Z",
        "natureza": "Acerto Entrada",
        "operacao": "CREDITO"
      }
    ]
  }
}