{
  "info": {
    "id": 2060,
    "code": "11233",
    "name": "UNICA 2,60X1,80 OXFORD LISO ROSE",
    "timestamp": "2026-05-05T20:05:12.964Z"
  },
  "data": {
    "Barreiro": [
      {
        "quantidade": 1,
        "data_evento": "2023-03-17T03:00:00.000Z",
        "natureza": "Transferência Entrada",
        "operacao": "CREDITO"
      },
      {
        "quantidade": 1,
        "data_evento": "2023-03-24T03:00:00.000Z",
        "natureza": "Venda",
        "operacao": "DEBITO"
      },
      {
        "quantidade": 1,
        "data_evento": "2023-04-22T03:00:00.000Z",
        "natureza": "Venda",
        "operacao": "DEBITO"
      },
      {
        "quantidade": 3,
        "data_evento": "2024-05-24T03:00:00.000Z",
        "natureza": "Transferência Entrada",
        "operacao": "CREDITO"
      },
      {
        "quantidade": 1,
        "data_evento": "2024-05-24T03:00:00.000Z",
        "natureza": "Venda",
        "operacao": "DEBITO"
      },
      {
        "quantidade": 1,
        "data_evento": "2024-05-28T03:00:00.000Z",
        "natureza": "Transferência Entrada",
        "operacao": "CREDITO"
      },
      {
        "quantidade": 1,
        "data_evento": "2024-05-29T03:00:00.000Z",
        "natureza": "Venda",
        "operacao": "DEBITO"
      },
      {
        "quantidade": 1,
        "data_evento": "2024-06-01T03:00:00.000Z",
        "natureza": "Venda",
        "operacao": "DEBITO"
      },
      {
        "quantidade": 1,
        "data_evento": "2024-06-03T03:00:00.000Z",
        "natureza": "Venda",
        "operacao": "DEBITO"
      },
      {
        "quantidade": 1,
        "data_evento": "2024-06-03T03:00:00.000Z",
        "natureza": "Transferência Entrada",
        "operacao": "CREDITO"
      },
      {
        "quantidade": 1,
        "data_evento": "2024-06-04T03:00:00.000Z",
        "natureza": "Venda",
        "operacao": "DEBITO"
      }
    ],
    "Venda Nova": [
      {
        "quantidade": 1,
        "data_evento": "2023-03-18T03:00:00.000Z",
        "natureza": "Venda",
        "operacao": "DEBITO"
      },
      {
        "quantidade": 1,
        "data_evento": "2023-06-26T03:00:00.000Z",
        "natureza": "Venda",
        "operacao": "DEBITO"
      },
      {
        "quantidade": 2,
        "data_evento": "2024-05-24T03:00:00.000Z",
        "natureza": "Transferência Entrada",
        "operacao": "CREDITO"
      },
      {
        "quantidade": 2,
        "data_evento": "2024-05-28T03:00:00.000Z",
        "natureza": "Venda",
        "operacao": "DEBITO"
      },
      {
        "quantidade": 1,
        "data_evento": "2024-06-03T03:00:00.000Z",
        "natureza": "Transferência Entrada",
        "operacao": "CREDITO"
      },
      {
        "quantidade": 1,
        "data_evento": "2024-06-06T03:00:00.000Z",
        "natureza": "Venda",
        "operacao": "DEBITO"
      }
    ],
    "Tupis": [
      {
        "quantidade": 1,
        "data_evento": "2023-03-27T03:00:00.000Z",
        "natureza": "Venda",
        "operacao": "DEBITO"
      },
      {
        "quantidade": 1,
        "data_evento": "2023-08-09T03:00:00.000Z",
        "natureza": "Acerto Saída",
        "operacao": "DEBITO"
      },
      {
        "quantidade": 2,
        "data_evento": "2024-05-24T03:00:00.000Z",
        "natureza": "Transferência Entrada",
        "operacao": "CREDITO"
      },
      {
        "quantidade": 1,
        "data_evento": "2024-05-27T03:00:00.000Z",
        "natureza": "Venda",
        "operacao": "DEBITO"
      },
      {
        "quantidade": 1,
        "data_evento": "2024-06-03T03:00:00.000Z",
        "natureza": "Transferência Entrada",
        "operacao": "CREDITO"
      },
      {
        "quantidade": 1,
        "data_evento": "2024-07-15T03:00:00.000Z",
        "natureza": "Venda",
        "operacao": "DEBITO"
      }
    ],
    "Guaranis": [
      {
        "quantidade": 2,
        "data_evento": "2023-04-01T03:00:00.000Z",
        "natureza": "Venda",
        "operacao": "DEBITO"
      },
      {
        "quantidade": 2,
        "data_evento": "2024-05-24T03:00:00.000Z",
        "natureza": "Transferência Entrada",
        "operacao": "CREDITO"
      },
      {
        "quantidade": 1,
        "data_evento": "2024-05-25T03:00:00.000Z",
        "natureza": "Venda",
        "operacao": "DEBITO"
      },
      {
        "quantidade": 1,
        "data_evento": "2024-05-28T03:00:00.000Z",
        "natureza": "Transferência Entrada",
        "operacao": "CREDITO"
      },
      {
        "quantidade": 1,
        "data_evento": "2024-06-05T03:00:00.000Z",
        "natureza": "Devolução de Venda",
        "operacao": "CREDITO"
      },
      {
        "quantidade": 1,
        "data_evento": "2024-06-13T03:00:00.000Z",
        "natureza": "Venda",
        "operacao": "DEBITO"
      },
      {
        "quantidade": 1,
        "data_evento": "2024-06-20T03:00:00.000Z",
        "natureza": "Venda",
        "operacao": "DEBITO"
      },
      {
        "quantidade": 1,
        "data_evento": "2024-08-08T03:00:00.000Z",
        "natureza": "Venda",
        "operacao": "DEBITO"
      }
    ],
    "G2": [
      {
        "quantidade": 1,
        "data_evento": "2023-05-06T03:00:00.000Z",
        "natureza": "Venda",
        "operacao": "DEBITO"
      },
      {
        "quantidade": 1,
        "data_evento": "2023-05-09T03:00:00.000Z",
        "natureza": "Devolução de Venda",
        "operacao": "CREDITO"
      },
      {
        "quantidade": 1,
        "data_evento": "2023-05-31T03:00:00.000Z",
        "natureza": "Venda",
        "operacao": "DEBITO"
      },
      {
        "quantidade": 1,
        "data_evento": "2023-06-02T03:00:00.000Z",
        "natureza": "Venda",
        "operacao": "DEBITO"
      },
      {
        "quantidade": 1,
        "data_evento": "2023-06-02T03:00:00.000Z",
        "natureza": "Devolução de Venda",
        "operacao": "CREDITO"
      },
      {
        "quantidade": 1,
        "data_evento": "2023-06-30T03:00:00.000Z",
        "natureza": "Venda",
        "operacao": "DEBITO"
      },
      {
        "quantidade": 1,
        "data_evento": "2023-07-10T03:00:00.000Z",
        "natureza": "Venda",
        "operacao": "DEBITO"
      },
      {
        "quantidade": 2,
        "data_evento": "2024-05-27T03:00:00.000Z",
        "natureza": "Transferência Entrada",
        "operacao": "CREDITO"
      },
      {
        "quantidade": 1,
        "data_evento": "2024-06-10T03:00:00.000Z",
        "natureza": "Venda",
        "operacao": "DEBITO"
      },
      {
        "quantidade": 1,
        "data_evento": "2024-08-29T03:00:00.000Z",
        "natureza": "Venda",
        "operacao": "DEBITO"
      }
    ],
    "Betim": [
      {
        "quantidade": 3,
        "data_evento": "2023-08-16T03:00:00.000Z",
        "natureza": "Acerto Saída",
        "operacao": "DEBITO"
      },
      {
        "quantidade": 2,
        "data_evento": "2024-05-24T03:00:00.000Z",
        "natureza": "Transferência Entrada",
        "operacao": "CREDITO"
      },
      {
        "quantidade": 1,
        "data_evento": "2024-06-13T03:00:00.000Z",
        "natureza": "Venda",
        "operacao": "DEBITO"
      },
      {
        "quantidade": 1,
        "data_evento": "2024-06-15T03:00:00.000Z",
        "natureza": "Venda",
        "operacao": "DEBITO"
      }
    ],
    "Babita": [
      {
        "quantidade": 2,
        "data_evento": "2023-09-21T03:00:00.000Z",
        "natureza": "Venda",
        "operacao": "DEBITO"
      },
      {
        "quantidade": 2,
        "data_evento": "2024-05-24T03:00:00.000Z",
        "natureza": "Transferência Entrada",
        "operacao": "CREDITO"
      },
      {
        "quantidade": 1,
        "data_evento": "2024-06-03T03:00:00.000Z",
        "natureza": "Venda",
        "operacao": "DEBITO"
      },
      {
        "quantidade": 1,
        "data_evento": "2025-02-17T03:00:00.000Z",
        "natureza": "Venda",
        "operacao": "DEBITO"
      }
    ],
    "Fábrica": [
      {
        "quantidade": 26,
        "data_evento": "2024-05-20T03:00:00.000Z",
        "natureza": "Entrada",
        "operacao": "CREDITO"
      },
      {
        "quantidade": 3,
        "data_evento": "2024-05-21T03:00:00.000Z",
        "natureza": "Transferência Saída Fábrica",
        "operacao": "DEBITO"
      },
      {
        "quantidade": 2,
        "data_evento": "2024-05-23T03:00:00.000Z",
        "natureza": "Transferência Saída Fábrica",
        "operacao": "DEBITO"
      },
      {
        "quantidade": 3,
        "data_evento": "2024-05-23T03:00:00.000Z",
        "natureza": "Transferência Saída Fábrica",
        "operacao": "DEBITO"
      },
      {
        "quantidade": 1,
        "data_evento": "2024-05-27T03:00:00.000Z",
        "natureza": "Transferência Saída Fábrica",
        "operacao": "DEBITO"
      },
      {
        "quantidade": 1,
        "data_evento": "2024-06-03T03:00:00.000Z",
        "natureza": "Transferência Saída Fábrica",
        "operacao": "DEBITO"
      }
    ],
    "Eldorado 2": [
      {
        "quantidade": 3,
        "data_evento": "2024-05-21T03:00:00.000Z",
        "natureza": "Transferência Entrada",
        "operacao": "CREDITO"
      },
      {
        "quantidade": 1,
        "data_evento": "2024-05-29T03:00:00.000Z",
        "natureza": "Venda",
        "operacao": "DEBITO"
      },
      {
        "quantidade": 1,
        "data_evento": "2024-06-20T03:00:00.000Z",
        "natureza": "Venda",
        "operacao": "DEBITO"
      },
      {
        "quantidade": 1,
        "data_evento": "2024-06-28T03:00:00.000Z",
        "natureza": "Venda",
        "operacao": "DEBITO"
      }
    ]
  }
}