{
  "info": {
    "id": 1772,
    "code": "11111",
    "name": "TEC CORTA LUZ EST. MARROM 2.80 MT",
    "timestamp": "2026-05-05T20:04:27.612Z"
  },
  "data": {
    "Fábrica": [
      {
        "quantidade": 6.821210263296962e-13,
        "data_evento": "2023-06-29T03:00:00.000Z",
        "natureza": "Acerto Entrada",
        "operacao": "CREDITO"
      },
      {
        "quantidade": 6.821210263296962e-13,
        "data_evento": "2024-01-23T03:00:00.000Z",
        "natureza": "Acerto Saída",
        "operacao": "DEBITO"
      }
    ]
  }
}