{
  "info": {
    "id": 3864,
    "code": "12990",
    "name": "CORTINA OUTLET -E2-",
    "timestamp": "2026-05-05T20:07:26.751Z"
  },
  "data": {
    "Tupis": [
      {
        "quantidade": 1,
        "data_evento": "2026-01-22T03:00:00.000Z",
        "natureza": "Venda",
        "operacao": "DEBITO"
      },
      {
        "quantidade": 1,
        "data_evento": "2026-01-29T03:00:00.000Z",
        "natureza": "Entrada",
        "operacao": "CREDITO"
      }
    ],
    "Barreiro": [
      {
        "quantidade": 1,
        "data_evento": "2026-02-10T03:00:00.000Z",
        "natureza": "Transferência Entrada",
        "operacao": "CREDITO"
      },
      {
        "quantidade": 1,
        "data_evento": "2026-03-03T03:00:00.000Z",
        "natureza": "Venda",
        "operacao": "DEBITO"
      }
    ],
    "Eldorado 2": [
      {
        "quantidade": 1,
        "data_evento": "2026-03-13T03:00:00.000Z",
        "natureza": "Venda",
        "operacao": "DEBITO"
      },
      {
        "quantidade": 3,
        "data_evento": "2026-04-24T03:00:00.000Z",
        "natureza": "Entrada",
        "operacao": "CREDITO"
      },
      {
        "quantidade": 1,
        "data_evento": "2026-04-27T03:00:00.000Z",
        "natureza": "Venda",
        "operacao": "DEBITO"
      }
    ],
    "Babita": [
      {
        "quantidade": 1,
        "data_evento": "2026-04-20T03:00:00.000Z",
        "natureza": "Venda",
        "operacao": "DEBITO"
      }
    ]
  }
}