{
  "info": {
    "id": 3662,
    "code": "12759",
    "name": "TUBO ILHOS 19MM CROMADO MT",
    "timestamp": "2026-04-30T11:37:56.789Z"
  },
  "data": {
    "Venda Nova": [
      {
        "quantidade": 1,
        "data_evento": "2024-09-20T03:00:00.000Z",
        "natureza": "Venda",
        "operacao": "DEBITO"
      },
      {
        "quantidade": 1,
        "data_evento": "2025-03-20T03:00:00.000Z",
        "natureza": "Venda",
        "operacao": "DEBITO"
      },
      {
        "quantidade": 2,
        "data_evento": "2025-07-14T03:00:00.000Z",
        "natureza": "Acerto Entrada",
        "operacao": "CREDITO"
      },
      {
        "quantidade": 1,
        "data_evento": "2025-07-16T03:00:00.000Z",
        "natureza": "Venda",
        "operacao": "DEBITO"
      }
    ],
    "Barreiro": [
      {
        "quantidade": 2,
        "data_evento": "2024-12-05T03:00:00.000Z",
        "natureza": "Venda",
        "operacao": "DEBITO"
      },
      {
        "quantidade": 2,
        "data_evento": "2025-07-14T03:00:00.000Z",
        "natureza": "Acerto Entrada",
        "operacao": "CREDITO"
      },
      {
        "quantidade": 1,
        "data_evento": "2025-12-23T03:00:00.000Z",
        "natureza": "Venda",
        "operacao": "DEBITO"
      },
      {
        "quantidade": 1,
        "data_evento": "2025-12-23T03:00:00.000Z",
        "natureza": "Venda",
        "operacao": "DEBITO"
      },
      {
        "quantidade": 1,
        "data_evento": "2025-12-29T03:00:00.000Z",
        "natureza": "Venda",
        "operacao": "DEBITO"
      },
      {
        "quantidade": 1,
        "data_evento": "2026-01-26T03:00:00.000Z",
        "natureza": "Venda",
        "operacao": "DEBITO"
      }
    ],
    "Guaranis": [
      {
        "quantidade": 1,
        "data_evento": "2025-05-16T03:00:00.000Z",
        "natureza": "Venda",
        "operacao": "DEBITO"
      },
      {
        "quantidade": 1,
        "data_evento": "2025-07-09T03:00:00.000Z",
        "natureza": "Acerto Entrada",
        "operacao": "CREDITO"
      }
    ],
    "G2": [
      {
        "quantidade": 1,
        "data_evento": "2025-09-04T03:00:00.000Z",
        "natureza": "Venda",
        "operacao": "DEBITO"
      }
    ],
    "Babita": [
      {
        "quantidade": 1,
        "data_evento": "2026-02-09T03:00:00.000Z",
        "natureza": "Venda",
        "operacao": "DEBITO"
      }
    ]
  }
}