{
  "info": {
    "id": 2260,
    "code": "11175",
    "name": "CABIDE REFORÇADO",
    "timestamp": "2026-05-05T20:05:44.582Z"
  },
  "data": {
    "Guaranis": [
      {
        "quantidade": 84,
        "data_evento": "2023-09-06T03:00:00.000Z",
        "natureza": "Acerto Entrada",
        "operacao": "CREDITO"
      }
    ],
    "G2": [
      {
        "quantidade": 33,
        "data_evento": "2023-09-06T03:00:00.000Z",
        "natureza": "Acerto Entrada",
        "operacao": "CREDITO"
      }
    ],
    "Venda Nova": [
      {
        "quantidade": 45,
        "data_evento": "2023-09-18T03:00:00.000Z",
        "natureza": "Acerto Entrada",
        "operacao": "CREDITO"
      }
    ],
    "Eldorado 2": [
      {
        "quantidade": 27,
        "data_evento": "2024-01-19T03:00:00.000Z",
        "natureza": "Venda",
        "operacao": "DEBITO"
      },
      {
        "quantidade": 18,
        "data_evento": "2024-01-26T03:00:00.000Z",
        "natureza": "Venda",
        "operacao": "DEBITO"
      },
      {
        "quantidade": 2,
        "data_evento": "2024-02-19T03:00:00.000Z",
        "natureza": "Venda",
        "operacao": "DEBITO"
      },
      {
        "quantidade": 47,
        "data_evento": "2025-07-14T03:00:00.000Z",
        "natureza": "Acerto Entrada",
        "operacao": "CREDITO"
      }
    ]
  }
}