{
  "info": {
    "id": 2905,
    "code": "11973",
    "name": "DUPLEX 4,00X2,60 LINHO EST FLOR BRANCO",
    "timestamp": "2026-04-30T11:35:54.106Z"
  },
  "data": {
    "Guaranis": [
      {
        "quantidade": 1,
        "data_evento": "2023-03-18T03:00:00.000Z",
        "natureza": "Venda",
        "operacao": "DEBITO"
      },
      {
        "quantidade": 1,
        "data_evento": "2023-05-13T03:00:00.000Z",
        "natureza": "Transferência Saída Loja",
        "operacao": "DEBITO"
      },
      {
        "quantidade": 1,
        "data_evento": "2023-07-25T03:00:00.000Z",
        "natureza": "Transferência Saída Loja",
        "operacao": "DEBITO"
      }
    ],
    "G2": [
      {
        "quantidade": 1,
        "data_evento": "2023-03-28T03:00:00.000Z",
        "natureza": "Venda",
        "operacao": "DEBITO"
      },
      {
        "quantidade": 1,
        "data_evento": "2023-05-13T03:00:00.000Z",
        "natureza": "Venda",
        "operacao": "DEBITO"
      },
      {
        "quantidade": 1,
        "data_evento": "2023-05-26T03:00:00.000Z",
        "natureza": "Venda",
        "operacao": "DEBITO"
      }
    ],
    "Betim": [
      {
        "quantidade": 1,
        "data_evento": "2023-06-30T03:00:00.000Z",
        "natureza": "Venda",
        "operacao": "DEBITO"
      }
    ],
    "Babita": [
      {
        "quantidade": 1,
        "data_evento": "2023-08-03T03:00:00.000Z",
        "natureza": "Venda",
        "operacao": "DEBITO"
      },
      {
        "quantidade": 1,
        "data_evento": "2023-08-12T03:00:00.000Z",
        "natureza": "Venda",
        "operacao": "DEBITO"
      }
    ],
    "Venda Nova": [
      {
        "quantidade": 1,
        "data_evento": "2023-09-12T03:00:00.000Z",
        "natureza": "Venda",
        "operacao": "DEBITO"
      }
    ]
  }
}