{
  "info": {
    "id": 705,
    "code": "8812",
    "name": "UNICA 2,60X1,80 MICROFIBRA TIFFANY",
    "timestamp": "2026-04-30T11:29:40.193Z"
  },
  "data": {
    "Guaranis": [
      {
        "quantidade": 1,
        "data_evento": "2023-05-02T03:00:00.000Z",
        "natureza": "Venda",
        "operacao": "DEBITO"
      },
      {
        "quantidade": 1,
        "data_evento": "2023-05-15T03:00:00.000Z",
        "natureza": "Venda",
        "operacao": "DEBITO"
      },
      {
        "quantidade": 1,
        "data_evento": "2023-06-27T03:00:00.000Z",
        "natureza": "Venda",
        "operacao": "DEBITO"
      }
    ],
    "G2": [
      {
        "quantidade": 1,
        "data_evento": "2023-05-24T03:00:00.000Z",
        "natureza": "Venda",
        "operacao": "DEBITO"
      },
      {
        "quantidade": 1,
        "data_evento": "2023-06-05T03:00:00.000Z",
        "natureza": "Venda",
        "operacao": "DEBITO"
      }
    ],
    "Venda Nova": [
      {
        "quantidade": 1,
        "data_evento": "2023-06-01T03:00:00.000Z",
        "natureza": "Acerto Saída",
        "operacao": "DEBITO"
      }
    ]
  }
}